asv/step_detect.py
asv/console.py
asv/runner.py
asv/config.py
asv/benchmark.py
asv/_version.py
asv/results.py
asv/util.py
asv/graph.py
asv/build_cache.py
asv/__init__.py
asv/feed.py
asv/publishing.py
asv/machine.py
asv/_rangemedian.cpp
asv/repo.py
asv/environment.py
asv/_stats.py
asv/_rangemedian.cpython-312-darwin.so
asv/main.py
asv/benchmarks.py
asv/__main__.py
asv/plugin_manager.py
asv/profiling.py
asv/plugins/git.py
asv/plugins/runsnake.py
asv/plugins/conda.py
asv/plugins/summarylist.py
asv/plugins/__init__.py
asv/plugins/summarygrid.py
asv/plugins/rattler.py
asv/plugins/mercurial.py
asv/plugins/kcachegrind.py
asv/plugins/regressions.py
asv/plugins/github.py
asv/plugins/virtualenv.py
asv/plugins/snakeviz.py
asv/template/asv.conf.json
asv/template/.gitignore
asv/template/benchmarks/__init__.py
asv/template/benchmarks/benchmarks.py
asv/www/summarylist.js
asv/www/graphdisplay.js
asv/www/index.html
asv/www/summarygrid.js
asv/www/asv.js
asv/www/asv_ui.js
asv/www/swallow.ico
asv/www/regressions.css
asv/www/summarylist.css
asv/www/asv.css
asv/www/regressions.js
asv/www/swallow.png
asv/www/error.html
asv/www/jquery.flot.axislabels.js
asv/commands/update.py
asv/commands/preview.py
asv/commands/show.py
asv/commands/run.py
asv/commands/check.py
asv/commands/__init__.py
asv/commands/rm.py
asv/commands/common_args.py
asv/commands/machine.py
asv/commands/setup.py
asv/commands/find.py
asv/commands/continuous.py
asv/commands/compare.py
asv/commands/quickstart.py
asv/commands/profiling.py
asv/commands/publish.py
asv-0.6.5.dist-info/RECORD
asv-0.6.5.dist-info/WHEEL
asv-0.6.5.dist-info/entry_points.txt
asv-0.6.5.dist-info/LICENSE.rst
asv-0.6.5.dist-info/top_level.txt
asv-0.6.5.dist-info/METADATA
