Metadata-Version: 2.1
Name: asv
Version: 0.6.5
Summary: Airspeed Velocity: A simple Python history benchmarking tool
Author-email: Michael Droettboom <mdroe@stsci.edu>
License: BSD-3-Clause
Project-URL: Source Code, https://github.com/airspeed-velocity/asv
Project-URL: Documentation, https://asv.readthedocs.io/en/stable/
Classifier: Development Status :: 5 - Production/Stable
Classifier: Environment :: Console
Classifier: Environment :: Web Environment
Classifier: License :: OSI Approved :: BSD License
Classifier: Operating System :: OS Independent
Classifier: Programming Language :: Python :: 3
Classifier: Programming Language :: Python :: 3 :: Only
Classifier: Programming Language :: Python :: 3.7
Classifier: Programming Language :: Python :: 3.8
Classifier: Programming Language :: Python :: 3.9
Classifier: Programming Language :: Python :: 3.10
Classifier: Programming Language :: Python :: 3.11
Classifier: Programming Language :: Python :: 3.12
Classifier: Topic :: Software Development :: Testing
Requires-Python: >=3.7
License-File: LICENSE.rst
Requires-Dist: asv-runner >=v0.2.1
Requires-Dist: json5
Requires-Dist: build
Requires-Dist: tabulate
Requires-Dist: virtualenv
Requires-Dist: packaging
Requires-Dist: importlib-metadata
Requires-Dist: pyyaml ; platform_python_implementation != "PyPy"
Requires-Dist: pympler ; platform_python_implementation != "PyPy"
Requires-Dist: colorama ; platform_system == "Windows"
Requires-Dist: tomli ; python_version < "3.11"
Provides-Extra: all
Requires-Dist: asv[dev,doc,envs,hg] ; extra == 'all'
Provides-Extra: dev
Requires-Dist: ruff ; extra == 'dev'
Provides-Extra: doc
Requires-Dist: sphinx ; extra == 'doc'
Requires-Dist: sphinx-autoapi ; extra == 'doc'
Requires-Dist: sphinx-collapse ; extra == 'doc'
Requires-Dist: sphinxcontrib.bibtex ; extra == 'doc'
Requires-Dist: setuptools ; extra == 'doc'
Requires-Dist: sphinxcontrib.katex ; extra == 'doc'
Requires-Dist: furo ; extra == 'doc'
Provides-Extra: envs
Requires-Dist: py-rattler ; extra == 'envs'
Provides-Extra: hg
Requires-Dist: python-hglib ; extra == 'hg'
Provides-Extra: plugs
Requires-Dist: asv-bench-memray ; extra == 'plugs'
Provides-Extra: test
Requires-Dist: pytest ; extra == 'test'
Requires-Dist: pytest-xdist ; extra == 'test'
Requires-Dist: pytest-timeout ; extra == 'test'
Requires-Dist: pytest-rerunfailures >=10.0 ; extra == 'test'
Requires-Dist: filelock ; extra == 'test'
Requires-Dist: numpy ; extra == 'test'
Requires-Dist: feedparser ; extra == 'test'
Requires-Dist: selenium ; extra == 'test'
Requires-Dist: flaky ; extra == 'test'
Requires-Dist: pytest-rerunfailures ; extra == 'test'
Requires-Dist: scipy ; (platform_python_implementation != "PyPy") and extra == 'test'
Requires-Dist: python-hglib ; (platform_system != "Windows") and extra == 'test'
Provides-Extra: testr
Requires-Dist: rpy2 ; (platform_system != "Windows" and platform_python_implementation != "PyPy") and extra == 'testr'
